{
  "eval_id": "cro_010",
  "run_id": "cro_010_without_skill",
  "expectations": [
    {
      "text": "Output follows the 4-section CRO format",
      "passed": true,
      "evidence": "Term coverage: 50% (1/2)"
    },
    {
      "text": "Evaluates the headline as strong and specific (includes 'free' and concrete outcome)",
      "passed": false,
      "evidence": "Term coverage: 38% (3/8)"
    },
    {
      "text": "Notes the form is well-optimized with only 4 fields (low friction)",
      "passed": true,
      "evidence": "Term coverage: 50% (2/4)"
    },
    {
      "text": "Recommends adding more social proof (customer count, specific results, testimonials)",
      "passed": false,
      "evidence": "Term coverage: 33% (3/9)"
    },
    {
      "text": "Suggests adding a preview of what the audit delivers (sample report, expected findings)",
      "passed": false,
      "evidence": "Term coverage: 22% (2/9)"
    },
    {
      "text": "Recommends adding a guarantee or risk reversal beyond 'no spam'",
      "passed": false,
      "evidence": "Term coverage: 0% (0/6)"
    },
    {
      "text": "Provides at least 2 test ideas specific to this lead gen form",
      "passed": false,
      "evidence": "Term coverage: 25% (1/4)"
    },
    {
      "text": "At least one copy alternative for the CTA that adds specificity or urgency",
      "passed": true,
      "evidence": "Has alternatives"
    },
    {
      "text": "Recommends addressing the 'what happens after I submit?' question",
      "passed": false,
      "evidence": "Term coverage: 29% (2/7)"
    },
    {
      "text": "Notes the page handles the traffic source well (B2B, senior roles, specific value prop)",
      "passed": true,
      "evidence": "Term coverage: 50% (5/10)"
    }
  ],
  "pass_rate": 0.4,
  "scores": {
    "specificity": 1.0,
    "actionability": 0.375,
    "structure": 0.85,
    "depth": 0.9447560975609757,
    "voice": 0.85,
    "composite": 0.6819756097560976,
    "word_count": 1597
  }
}