{
  "eval_id": "copy_010",
  "run_id": "copy_010_without_skill",
  "expectations": [
    {
      "text": "Output contains Headline, Subheadline, CTA, and at least 2 headline alternatives",
      "passed": true,
      "evidence": "Has alternatives"
    },
    {
      "text": "Headline addresses the emotional pain (guilt, worry about pet) not just the service",
      "passed": true,
      "evidence": "Term coverage: 57% (4/7)"
    },
    {
      "text": "Copy communicates trust and safety (background checks, certification, video meet) without sounding clinical",
      "passed": false,
      "evidence": "Term coverage: 36% (4/11)"
    },
    {
      "text": "Subheadline adds specificity (mentions a verification detail or the meet-and-greet feature)",
      "passed": false,
      "evidence": "Term coverage: 43% (3/7)"
    },
    {
      "text": "CTA communicates the outcome (e.g., 'Find My Pet Sitter' not 'Browse Sitters')",
      "passed": false,
      "evidence": "Term coverage: 0% (0/7)"
    },
    {
      "text": "Copy uses customer language and emotional resonance ('peace of mind', 'like family')",
      "passed": false,
      "evidence": "Term coverage: 12% (1/8)"
    },
    {
      "text": "At least one headline alternative uses the '{Achieve outcome} without {pain point}' formula",
      "passed": true,
      "evidence": "Has alternatives"
    },
    {
      "text": "No exclamation points",
      "passed": true,
      "evidence": "No banned phrases found"
    },
    {
      "text": "Active voice used throughout",
      "passed": false,
      "evidence": "Term coverage: 0% (0/3)"
    },
    {
      "text": "Annotations explain the emotional approach chosen for this audience",
      "passed": false,
      "evidence": "Missing annotations"
    }
  ],
  "pass_rate": 0.4,
  "scores": {
    "specificity": 0.7166666666666666,
    "actionability": 0.0,
    "structure": 0.85,
    "depth": 0.6330769230769231,
    "voice": 0.94,
    "composite": 0.5281410256410256,
    "word_count": 519
  }
}