{
  "eval_id": "cro_007",
  "run_id": "cro_007_with_skill",
  "expectations": [
    {
      "text": "Output follows the Quick Wins / High-Impact Changes / Test Ideas / Copy Alternatives structure",
      "passed": true,
      "evidence": "Has alternatives"
    },
    {
      "text": "Identifies the form has too many fields for a signup flow (8 fields + checkbox)",
      "passed": true,
      "evidence": "Term coverage: 60% (3/5)"
    },
    {
      "text": "Recommends reducing to essential fields (email, password, name) and collecting the rest post-signup",
      "passed": true,
      "evidence": "Term coverage: 56% (5/9)"
    },
    {
      "text": "Notes the headline 'Create Your Account' is functional but not motivating",
      "passed": false,
      "evidence": "Term coverage: 33% (2/6)"
    },
    {
      "text": "Recommends adding a benefit-oriented headline or subheadline",
      "passed": true,
      "evidence": "Term coverage: 60% (3/5)"
    },
    {
      "text": "Identifies the absence of social proof near the signup form",
      "passed": true,
      "evidence": "Term coverage: 80% (4/5)"
    },
    {
      "text": "Recommends adding a free trial mention or risk reversal near the CTA",
      "passed": true,
      "evidence": "Term coverage: 80% (4/5)"
    },
    {
      "text": "Provides at least 2 alternative CTA buttons (not just 'Create Account')",
      "passed": true,
      "evidence": "Has alternatives"
    },
    {
      "text": "Suggests splitting into multi-step form if many fields are truly required",
      "passed": true,
      "evidence": "Term coverage: 50% (3/6)"
    },
    {
      "text": "At least one recommendation addresses reducing perceived commitment",
      "passed": true,
      "evidence": "Term coverage: 83% (5/6)"
    }
  ],
  "pass_rate": 0.9,
  "scores": {
    "specificity": 1.0,
    "actionability": 0.575,
    "structure": 0.85,
    "depth": 0.9268205128205128,
    "voice": 0.85,
    "composite": 0.8451820512820513,
    "word_count": 3448
  }
}